simple/Request.py
simple/Server.py
simple/Service.py
simple/__init__.py
simple_grpc-0.0.1.dev0.dist-info/LICENSE
simple_grpc-0.0.1.dev0.dist-info/METADATA
simple_grpc-0.0.1.dev0.dist-info/WHEEL
simple_grpc-0.0.1.dev0.dist-info/top_level.txt
simple_grpc-0.0.1.dev0.dist-info/RECORD
